ComfeePool/ComfeeApplianceMapper.py
ComfeePool/ComfeeConfig.py
ComfeePool/ComfeeDehumidifierMapper.py
ComfeePool/__init__.py
ComfeePool/const.py
ComfeePool/example.py
comfeepool-0.1.1.dist-info/WHEEL
comfeepool-0.1.1.dist-info/METADATA
comfeepool-0.1.1.dist-info/RECORD
