Metadata-Version: 2.1
Name: ComfeePool
Version: 0.1.1
Summary: A package to integrate Comfee Dehumidifiers with MQTT Broker.
Author-email: ftcid <fernando.tor.c@gmail.com>
Requires-Python: >=3.7
Classifier: Programming Language :: Python :: 3
Classifier: License :: OSI Approved :: Apache Software License
Classifier: Operating System :: OS Independent
Project-URL: Homepage, https://github.com/ftcid
Project-URL: Issues, https://github.com/ftcid
